Workbook
Name NativeTimeline_Order_Date: #N/A
Name Slicer_Category: #N/A
Name Slicer_Region: #N/A

Sheet Sales_Data
A1: Order_ID | B1: Customer_ID | C1: Product_ID | D1: Order_Date | E1: Delivery_Date | F1: Customer_Name | G1: Gender | H1: DOB | I1: City | J1: Region | K1: Category | L1: Product_Name | M1: Quantity | N1: Unit_Price | O1: Discount_% | P1: Sales | Q1: Rating | R1: Payment_Mode | S1: Salesperson | T1: Email | U1: Phone | V1: Order_Status
A2: ORD10001 | B2: C008 | C2: P202 | D2: 45918 | E2: 45922 | F2: Kavya Nair | G2: Female | H2: 27973 | I2: Hyderabad | J2: South | K2: Home Appliances | L2: Iron | M2: 4 | N2: 2200 | O2: 10 | P2: 7920 | Q2: 4 | R2: Cash | S2: Ritika | T2: KAvya.nair@company.com | U2: 9431429797 | V2: Completed
A3: ORD10002 | B3: C008 | C3: P104 | D3: 45774 | E3: 45781 | F3: Kavya Nair | G3: Female | H3: 36815 | I3: Delhi | J3: North | K3: Electronics | L3: Monitor | M3: 17 | N3: 12000 | O3: 10 | P3: 183600 | Q3: 1 | R3: NetBanking | S3: Rahul | T3: kavya.nair@company.com | U3: 9129865339 | V3: Completed
A4: ORD10003 | B4: C010 | C4: P101 | D4: 45903 | E4: 45914 | F4: pooja shah | G4: Female | H4: 34593 | I4: Bengaluru | J4: South | K4: Electronics | L4: Laptop | M4: 5 | N4: 55000 | O4: 5 | P4: 261250 | Q4: 3 | R4: NetBanking | S4: Aisha | T4: pooja.shah@company.com | U4: 9380975626 | V4: Pending
A5: ORD10002 | B5: C008 | C5: P202 | D5: 46102 | E5: 46114 | F5: Kavya Nair | G5: Female | H5: 38053 | I5: Bengaluru | J5: South | K5: Home Appliances | L5: Iron | M5: 5 | N5: 2200 | O5: 5 | P5: 10450 | Q5: 5 | R5: NetBanking | S5: Aisha | T5: kavya.nair@company.com | U5: 9600261125 | V5: Cancelled
A6: ORD10005 | B6: C009 | C6: P103 | D6: 45927 | E6: 45937 | F6: Mohit Verma | G6: Male | H6: 27863 | I6: Delhi | J6: North | K6: Electronics | L6: Keyboard | M6: 8 | N6: 1200 | O6: 5 | P6: 9120 | Q6: 2 | R6: Card | S6: Aisha | T6: mohit.verma@company.com | U6: 9724635978 | V6: Pending
A7: ORD10006 | B7: C007 | C7: P202 | D7: 46026 | E7: 46034 | F7: arjun Rao | G7: Male | H7: 32180 | I7: Hyderabad | J7: South | K7: Home Appliances | L7: Iron | M7: 4 | N7: 2200 | O7: 0 | P7: 8800 | Q7: 1 | R7: UPI | S7: Ritika | T7: arjun.rao@company.com | U7: 9780584905 | V7: Completed
A8: ORD10007 | B8: C008 | C8: P201 | D8: 31/02/2025 | E8: 46078 | F8: Kavya Nair | G8: Female | H8: 37700 | I8: Hyderabad | J8: South | K8: Home Appliances | L8: Mixer | M8: 2 | N8: 3500 | O8: 5 | P8: 6650 | Q8: 1 | R8: UPI | S8: Ritika | T8: kavya.nair@company.com | U8: 9958252176 | V8: Completed
A9: ORD10008 | B9: C002 | C9: P104 | D9: 45760 | E9: 45766 | F9: Priya Patel | G9: Female | H9: 34765 | I9: Mumbai | J9: West | K9: Electronics | L9: Monitor | M9: 14 | N9: 12000 | O9: 15 | P9: 142800 | Q9: 4 | R9: NetBanking | S9: Ritika | T9: priYa.patel@company.com | U9: 9705521654 | V9: Completed
A10: ORD10009 | B10: C008 | C10: P104 | D10: 46053 | E10: 46055 | F10: kavya Nair | G10: Female | H10: 35526 | I10: Pune | J10: West | K10: Electronics | L10: Monitor | M10: 4 | N10: 12000 | O10: 15 | P10: 40800 | Q10: 4 | R10: UPI | S10: Neha | T10: kavya.nair@company.com | U10: 9588041011 | V10: Completed
A11: ORD10010 | B11: C002 | C11: P301 | D11: 45741 | E11: 45743 | F11: Priya Patel | G11: Female | H11: 32880 | I11: Mumbai | J11: West | K11: Stationery | L11: Notebook | M11: 6 | N11: 60 | O11: 0 | P11: 360 | Q11: 4 | R11: Card | S11: Neha | T11: PRiya.patel@company.com | U11: 9340540608 | V11: Completed
A12: ORD10011 | B12: C003 | C12: P202 | D12: 45919 | E12: 45923 | F12: Rohit Singh | G12: Male | H12: 30081 | I12: Delhi | J12: North | K12: Home Appliances | L12: Iron | M12: -3 | N12: 2200 | O12: 0 | P12: 35200 | Q12: 2 | R12: Card | S12: Rahul | T12: rohit.singh@company.com | U12: 9521710321 | V12: Pending
A13: ORD10012 | B13: C008 | C13: P201 | D13: 45724 | E13: 45731 | F13: Kavya Nair | G13: Female | H13: 29974 | I13: Ahmedabad | J13: West | K13: Home Appliances | L13: Mixer | M13: 10 | N13: 3500 | O13: 5 | P13: 33250 | Q13: 5 | R13: Card | S13: Aisha | T13: kavya.nair@company.com | U13: 9123535241 | V13: Cancelled
A14: ORD10013 | B14: C002 | C14: P202 | D14: 45667 | E14: 45672 | F14: Priya Patel | G14: Female | H14: 33791 | I14: Pune | J14: West | K14: Home Appliances | L14: Iron | M14: 15 | N14: 2200 | O14: 10 | P14: 29700 | Q14: 1 | R14: UPI | S14: Neha | T14: priya.patel@company.com | U14: 9367316892 | V14: Pending
A15: ORD10014 | B15: C003 | C15: P202 | D15: 45725 | E15: 45729 | F15: rohit Singh | G15: Male | H15: 37334 | I15: Mumbai | J15: West | K15: Home Appliances | L15: Iron | M15: 17 | N15: 2200 | O15: 5 | P15: 35530 | Q15: 1 | R15: Cash | S15: Karan | T15: rOhit.singh@company.com | U15: 9778489803 | V15: Completed
A16: ORD10015 | B16: C008 | C16: P201 | D16: 45864 | E16: 45876 | F16: Kavya nair | G16: Female | H16: 36908 | I16: Mumbai | J16: West | K16: Home Appliances | L16: Mixer | M16: 15 | N16: 3500 | O16: 15 | P16: 44625 | Q16: 2 | R16: Cash | S16: Neha | T16: kavya.nair@company.com | U16: 9582960180 | V16: Cancelled
A17: ORD10016 | B17: C010 | C17: P103 | D17: 46120 | E17: 46123 | F17: Pooja Shah | G17: Female | H17: 37357 | I17: Hyderabad | J17: South | K17: Electronics | L17: Keyboard | M17: 3 | N17: 1200 | O17: 5 | P17: 3420 | Q17: 5 | R17: UPI | S17: Ritika | T17: pooja.shahcompany.com | U17: 9611394005 | V17: Completed
A18: ORD10017 | B18: C004 | C18: P203 | D18: 46075 | E18: 46084 | F18: Amit Sharma | G18: Female | H18: 37272 | I18: Pune | J18: West | K18: Home Appliances | L18: Microwave | M18: 13 | N18: 8500 | O18: 20 | P18: 88400 | Q18: 4 | R18: Card | S18: Rahul | T18: anita.gupta@company.com | U18: 9692599404 | V18: Pending
A19: ORD10018 | B19: C007 | C19: P203 | D19: 46081 | E19: 46086 | F19: Arjun Rao | G19: Male | H19: 32790 | I19: Ahmedabad | J19: West | K19: Home Appliances | L19: Microwave | M19: 4 | N19: 8500 | O19: 20 | P19: 27200 | Q19: 5 | R19: Card | S19: Aisha | T19: arjun.rao@company.com | U19: 9426119622 | V19: Pending
A20: ORD10019 | B20: C007 | C20: P102 | D20: 45992 | E20: 45995 | F20: arjun rao | G20: Male | H20: 33539 | I20: Mumbai | J20: West | K20: Electronics | L20: Mouse | M20: 9 | N20: 700 | O20: 5 | P20: 5985 | Q20: 3 | R20: UPI | S20: Ritika | T20: arjun.Rao@company.com | U20: 9184436009 | V20: Pending
... A49: ORD10048 | B49: C006 | C49: P102 | D49: 45988 | E49: 45994 | F49: Sneha Joshi | G49: Female | H49: 36125 | I49: Jaipur | J49: North | K49: Electronics | L49: Mouse | M49: 19 | N49: 700 | O49: 20 | P49: 10640 | Q49: 1 | R49: Cash | S49: Neha | T49: sneha.joshi@company.com | U49: 9238141322 | V49: Completed
A50: ORD10049 | B50: C009 | C50: P104 | D50: 46131 | F50: Mohit Verma | G50: Male | H50: 35219 | I50: Delhi | J50: North | K50: Electronics | L50: Monitor | M50: 19 | N50: 12000 | O50: 0 | P50: 228000 | Q50: 1 | R50: NetBanking | S50: Aisha | T50: mohit.verma@company.com | U50: 9890380030 | V50: Completed
A51: ORD10050 | B51: C004 | C51: P103 | D51: 46131 | E51: 46133 | F51: Anita Gupta | G51: Female | H51: 31851 | I51: Pune | J51: West | K51: Electronics | L51: Keyboard | M51: 6 | N51: 1200 | O51: 5 | P51: 6840 | Q51: 2 | R51: Cash | S51: Ritika | T51: anita.gupta@company.com | U51: 9495893170 | V51: Pending
A52: ORD10051 | B52: C010 | C52: P202 | D52: 45744 | E52: 45754 | F52: POoja Shah | G52: Female | H52: 28906 | I52: Bengaluru | J52: South | K52: Home Appliances | L52: Iron | M52: 7 | N52: 2200 | O52: 15 | P52: 13090 | Q52: 1 | R52: UPI | S52: Aisha | T52: pooja.shah@company.com | U52: 9485166307 | V52: Completed
A53: ORD10052 | B53: C002 | C53: P301 | D53: 45894 | E53: 45897 | F53: Priya Patel | G53: Female | H53: 36747 | I53: Jaipur | J53: North | K53: Stationery | L53: Notebook | M53: 8 | N53: 60 | O53: 10 | P53: 432 | Q53: 5 | R53: Card | S53: Aisha | T53: priya.patel@company.com | U53: 9924709648 | V53: Cancelled
A54: ORD10053 | B54: C005 | C54: P101 | D54: 45888 | E54: 45892 | F54: Vikas Mehta | G54: Male | H54: 27776 | I54: Kolkata | J54: East | K54: Electronics | L54: Laptop | M54: 12 | N54: 55000 | O54: 5 | P54: 627000 | Q54: 2 | R54: UPI | S54: Rahul | T54: vikas.mehta@company.com | U54: 9350554626 | V54: Pending
A55: ORD10054 | B55: C008 | C55: P102 | D55: 45865 | E55: 45874 | F55: Kavya Nair | G55: Female | H55: 27488 | I55: Jaipur | J55: North | K55: Electronics | L55: Mouse | M55: 3 | N55: 700 | O55: 0 | P55: 2100 | Q55: 3 | R55: Card | S55: Karan | T55: kavya.nair@company.com | U55: 9743295580 | V55: Cancelled
A56: ORD10055 | B56: C003 | C56: P301 | D56: 45709 | E56: 45714 | F56: RoHit Singh | G56: Male | H56: 28105 | I56: Ahmedabad | J56: West | K56: Stationery | L56: Notebook | M56: 19 | N56: 60 | O56: 15 | P56: 969 | Q56: 4 | R56: Card | S56: Rahul | T56: rohit.singh@company.com | U56: 9822926495 | V56: Cancelled
A57: ORD10056 | B57: C001 | C57: P301 | D57: 45879 | E57: 45880 | F57: Amit Sharma | G57: Male | H57: 29192 | I57: Jaipur | J57: North | K57: Stationery | L57: Notebook | M57: 9 | N57: 60 | O57: 20 | P57: 432 | Q57: 1 | R57: NetBanking | S57: Neha | T57: amit.sharma@company.com | U57: 9518298190 | V57: Pending
A58: ORD10057 | B58: C001 | C58: P102 | D58: 46105 | E58: 46111 | F58: Amit Sharma | G58: Male | H58: 28851 | I58: Bengaluru | J58: South | K58: Electronics | L58: Mouse | M58: 6 | N58: 700 | O58: 0 | P58: 4200 | Q58: 4 | R58: UPI | S58: Rahul | T58: amit.sharmcompany.com | U58: 9366223547 | V58: Cancelled
A59: ORD10058 | B59: C003 | C59: P303 | D59: 46094 | E59: 46100 | F59: Rohit Singh | G59: Male | H59: 27499 | I59: Delhi | J59: North | K59: Stationery | L59: Marker | M59: 18 | N59: 45 | O59: 5 | P59: 769.5 | Q59: 1 | R59: Card | S59: Aisha | T59: rohit.singh@company.com | U59: 9701988524 | V59: Pending
A60: ORD10059 | B60: C007 | C60: P302 | D60: 45823 | E60: 45834 | F60: Arjun Rao | G60: Male | H60: 32496 | I60: Jaipur | J60: North | K60: Stationery | L60: Pen | M60: 8 | N60: 20 | O60: 5 | P60: 152 | Q60: 1 | R60: Card | S60: Ritika | T60: arjun.rao@company.com | U60: 9836327649 | V60: completed
A61: ORD10060 | B61: C005 | C61: P102 | D61: 45721 | E61: 45722 | F61: Vikas Mehta | G61: Male | H61: 28921 | I61: Jaipur | J61: North | K61: Electronics | L61: Mouse | M61: 8 | N61: 700 | O61: 10 | P61: 5040 | Q61: 1 | R61: NetBanking | S61: Aisha | T61: Vikas.mehta@company.com | U61: 9261800516 | V61: Cancelled
A62: ORD10061 | B62: C008 | C62: P302 | D62: 46121 | E62: 46131 | F62: Kavya Nair | G62: Female | H62: 37972 | I62: Delhi | J62: North | K62: Stationery | L62: Pen | M62: 7 | N62: 20 | O62: 15 | P62: 119 | Q62: 5 | R62: Card | S62: Rahul | T62: kavya.nair@company.com | U62: 9950802015 | V62: Completed
... A74: ORD10073 | B74: C008 | C74: P103 | D74: 46004 | E74: 46014 | F74: Kavya Nair | G74: Female | H74: 29851 | I74: Jaipur | J74: North | K74: Electronics | L74: Keyboard | M74: 1 | N74: 1200 | O74: 5 | P74: 1140 | Q74: 3 | R74: UPI | S74: Aisha | T74: kavya.nair@company.com | U74: 9808988530 | V74: Cancelled
A75: ORD10074 | B75: C010 | C75: P202 | D75: 46057 | E75: 46069 | F75: Pooja Shah | G75: Female | H75: 29392 | J75: South | K75: Home Appliances | L75: Iron | M75: 1 | N75: 2200 | O75: 15 | P75: 1870 | Q75: 4 | R75: Card | S75: Aisha | T75: pooja.shah@company.com | U75: 9286410494 | V75: Completed
A76: ORD10075 | B76: C003 | C76: P103 | D76: 46048 | E76: 46050 | F76: Rohit Singh | G76: Male | H76: 30257 | I76: Pune | J76: West | K76: Electronics | L76: Keyboard | M76: 3 | N76: 1200 | O76: 10 | P76: 3240 | Q76: 5 | R76: Cash | S76: Rahul | T76: rohit.singh@company.com | U76: 9311555196 | V76: Completed
A77: ORD10076 | B77: C008 | C77: P201 | D77: 45835 | E77: 45845 | F77: Kavya Nair | G77: Female | H77: 29230 | I77: Bengaluru | J77: South | K77: Home Appliances | L77: Mixer | M77: 10 | N77: 3500 | O77: 20 | P77: 28000 | Q77: 5 | R77: Card | S77: Ritika | T77: kavya.nair@company.com | U77: 9101810266 | V77: Completed
A78: ORD10077 | B78: C007 | C78: P102 | D78: 46098 | E78: 46100 | F78: Arjun Rao | G78: Male | H78: 29703 | I78: Delhi | J78: North | K78: Electronics | L78: Mouse | M78: 18 | N78: 700 | O78: 5 | P78: 11970 | Q78: 3 | R78: Card | S78: Neha | T78: arjun.rao@company.com | U78: 9464556593 | V78: Cancelled
A79: ORD10078 | B79: C005 | C79: P102 | D79: 45817 | E79: 45826 | F79: Vikas Mehta | G79: Male | H79: 31118 | I79: Bengaluru | J79: South | K79: Electronics | L79: Mouse | M79: 12 | N79: 700 | O79: 15 | P79: 7140 | Q79: 2 | R79: UPI | S79: Rahul | T79: vikas.mehta@company.com | U79: 9338278358 | V79: Completed
A80: ORD10079 | B80: C009 | C80: P103 | D80: 45976 | E80: 45977 | F80: Mohit Verma | G80: Male | H80: 36234 | I80: Mumbai | J80: West | K80: Electronics | L80: Keyboard | M80: 8 | N80: 1200 | O80: 0 | P80: 9600 | Q80: 4 | R80: Card | S80: Rahul | T80: mohit.verma@company.com | U80: 9621410770 | V80: Pending
A81: ORD10080 | B81: C003 | C81: P301 | D81: 45967 | E81: 45971 | F81: Rohit Singh | G81: Male | H81: 30504 | I81: Pune | J81: West | K81: Stationery | L81: Notebook | M81: 2 | N81: 60 | O81: 0 | P81: 120 | Q81: 2 | R81: UPI | S81: Rahul | T81: rohit.singh@company.com | U81: 9981333189 | V81: Completed
A82: ORD10081 | B82: C001 | C82: P303 | D82: 45658 | E82: 45664 | F82: Amit Sharma | G82: Male | H82: 32573 | I82: Pune | J82: West | K82: Stationery | L82: Marker | M82: 10 | N82: 45 | O82: 15 | P82: 382.5 | Q82: 3 | R82: NetBanking | S82: Ritika | T82: amit.sharma@company.com | U82: 9723450355 | V82: Cancelled
A83: ORD10082 | B83: C005 | C83: P201 | D83: 46137 | E83: 46145 | F83: Vikas Mehta | G83: Male | H83: 30122 | I83: Kolkata | J83: East | K83: Home Appliances | L83: Mixer | M83: 12 | N83: 3500 | O83: 5 | P83: 39900 | Q83: 3 | R83: NetBanking | S83: Aisha | T83: vikas.mehta@company.com | U83: 9886243907 | V83: Pending
A84: ORD10083 | B84: C003 | C84: P301 | D84: 45919 | E84: 45927 | F84: Rohit Singh | G84: Male | H84: 37065 | I84: Mumbai | J84: West | K84: Stationery | L84: Notebook | M84: 2 | N84: 60 | O84: 15 | P84: 102 | Q84: 1 | R84: UPI | S84: Neha | T84: rohit.singh@company.com | U84: 9473931904 | V84: Completed
A85: ORD10084 | B85: C003 | C85: P103 | D85: 45734 | E85: 45737 | F85: Rohit Singh | G85: Male | H85: 30516 | I85: Hyderabad | J85: South | K85: Electronics | L85: Keyboard | M85: 18 | N85: 1200 | O85: 15 | P85: 18360 | Q85: 3 | R85: Card | S85: Neha | T85: rohit.singh@company.com | U85: 9287159610 | V85: Pending
A86: ORD10085 | B86: C008 | C86: P104 | D86: 45960 | E86: 45961 | F86: Kavya Nair | G86: Female | H86: 34052 | I86: Mumbai | J86: West | K86: Electronics | L86: Monitor | M86: 18 | N86: 12000 | O86: 15 | P86: 183600 | Q86: 2 | R86: Cash | S86: Rahul | T86: kavya.nair@company.com | U86: 9876513858 | V86: Completed
A87: ORD10086 | B87: C007 | C87: P302 | D87: 45961 | E87: 45972 | F87: Arjun Rao | G87: Male | H87: 34829 | I87: Ahmedabad | J87: West | K87: Stationery | L87: Pen | M87: 7 | N87: 20 | O87: 0 | P87: 140 | Q87: 2 | R87: Card | S87: Ritika | T87: arjun.rao@company.com | U87: 9237400853 | V87: Cancelled
... A119: ORD10118 | B119: C001 | C119: P303 | D119: 45808 | E119: 45819 | F119: Amit Sharma | G119: Male | H119: 34949 | I119: Pune | J119: West | K119: Stationery | L119: Marker | M119: 16 | N119: 45 | O119: 0 | P119: 720 | Q119: 1 | R119: NetBanking | S119: Aisha | T119: amit.sharma@company.com | U119: 9807154421 | V119: Completed
A120: ORD10119 | B120: C009 | C120: P103 | D120: 45807 | E120: 45810 | F120: Mohit Verma | G120: Male | H120: 32210 | I120: Ahmedabad | J120: West | K120: Electronics | L120: Keyboard | M120: Ten | N120: 1200 | O120: 15 | P120: 7140 | Q120: 4 | R120: UPI | S120: Karan | T120: mohit.verma@company.com | U120: 9919834000 | V120: Pending
A121: ORD10120 | B121: C002 | C121: P104 | D121: 45888 | E121: 45899 | F121: Priya Patel | G121: Female | H121: 32696 | I121: Jaipur | J121: North | K121: Electronics | L121: Monitor | M121: 14 | N121: 12000 | O121: 15 | P121: 142800 | Q121: 2 | R121: NetBanking | S121: Aisha | T121: priya.patel@company.com | U121: 9739798818 | V121: Pending
A122: ORD10121 | B122: C003 | C122: P203 | D122: 46005 | E122: 46007 | F122: Rohit Singh | G122: Male | H122: 34284 | I122: Pune | J122: West | K122: Home Appliances | L122: Microwave | M122: 8 | N122: 8500 | O122: 20 | P122: 54400 | Q122: 3 | R122: Card | S122: Rahul | T122: rohit.singh@company.com | U122: 9208625306 | V122: Completed
A123: ORD10122 | B123: C007 | C123: P303 | D123: 46053 | E123: 46063 | F123: Arjun Rao | G123: Male | H123: 36557 | I123: Bengaluru | J123: South | K123: Stationery | L123: Marker | M123: 3 | N123: 45 | O123: 0 | P123: 135 | Q123: 4 | R123: UPI | S123: Aisha | T123: arjun.rao@company.com | U123: 9970178536 | V123: Cancelled
A124: ORD10123 | B124: C001 | C124: P102 | D124: 46025 | E124: 46026 | F124: Amit Sharma | G124: Male | H124: 31585 | I124: Jaipur | J124: North | K124: Electronics | L124: Mouse | M124: 13 | N124: 700 | O124: 5 | P124: 8645 | Q124: 3 | R124: Card | S124: Neha | T124: amit.sharma@company.com | U124: 9633745195 | V124: Pending
A125: ORD10124 | B125: C004 | C125: P103 | D125: 45950 | E125: 45956 | F125: Anita Gupta | G125: Female | H125: 31459 | I125: Mumbai | J125: West | K125: Electronics | L125: Keyboard | M125: 14 | N125: 1200 | O125: 20 | P125: 13440 | Q125: 5 | R125: NetBanking | S125: Aisha | T125: anita.gupta@company.com | U125: 9922102053 | V125: Completed
A126: ORD10125 | B126: C002 | C126: P303 | D126: 45788 | E126: 45798 | F126: Priya Patel | G126: Female | H126: 33499 | I126: Delhi | J126: North | K126: Stationery | L126: Marker | M126: 2 | N126: 45 | O126: 5 | P126: 85.5 | Q126: 3 | R126: UPI | S126: Ritika | T126: priya.patel@company.com | U126: 9135963930 | V126: Cancelled
A127: ORD10126 | B127: C004 | C127: P103 | D127: 46024 | E127: 46028 | F127: Anita Gupta | G127: Female | H127: 29590 | I127: Bengaluru | J127: South | K127: Electronics | L127: Keyboard | M127: 2 | N127: 1200 | O127: 20 | P127: 1920 | Q127: 3 | R127: Card | S127: Neha | T127: anita.gupta@company.com | U127: 9429405275 | V127: Completed
A128: ORD10127 | B128: C003 | C128: P101 | D128: 46132 | E128: 46138 | F128: Rohit Singh | G128: Male | H128: 38272 | I128: Bengaluru | J128: South | K128: Electronics | L128: Laptop | M128: 10 | N128: 55000 | O128: 5 | P128: 522500 | Q128: 5 | R128: UPI | S128: Aisha | T128: rohit.singh@company.com | U128: 9521757571 | V128: Pending
A129: ORD10128 | B129: C006 | C129: P201 | D129: 45873 | E129: 45874 | F129: Sneha Joshi | G129: Female | H129: 30766 | I129: Jaipur | J129: North | K129: Home Appliances | L129: Mixer | M129: 15 | N129: 3500 | O129: 10 | P129: 47250 | Q129: 3 | R129: NetBanking | S129: Neha | T129: sneha.joshi@company.com | U129: 9467375455 | V129: Completed
A130: ORD10129 | B130: C002 | C130: P202 | D130: 45882 | E130: 45887 | F130: Priya Patel | G130: Female | H130: 30203 | I130: Bengaluru | J130: South | K130: Home Appliances | L130: Iron | M130: 10 | N130: 2200 | O130: 15 | P130: 18700 | Q130: 4 | R130: Card | S130: Rahul | T130: priya.patel@company.com | U130: 9838809695 | V130: Pending
A131: ORD10130 | B131: C006 | C131: P201 | D131: 45824 | E131: 45832 | F131: Sneha Joshi | G131: Female | H131: 34015 | I131: Pune | J131: West | K131: Home Appliances | L131: Mixer | M131: 11 | N131: 3500 | O131: 5 | P131: 36575 | Q131: 5 | R131: Cash | S131: Ritika | T131: sneha.joshi@company.com | U131: 9296609782 | V131: Cancelled
A132: ORD10131 | B132: C004 | C132: P103 | D132: 46139 | E132: 46142 | F132: Anita Gupta | G132: Female | H132: 37719 | I132: Bengaluru | J132: South | K132: Electronics | L132: Keyboard | M132: 14 | N132: 1200 | O132: 0 | P132: 16800 | Q132: 5 | R132: Cash | S132: Rahul | T132: anita.gupta@company.com | U132: 9848259992 | V132: Cancelled
... A299: ORD10298 | B299: C003 | C299: P101 | D299: 45670 | E299: 45673 | F299: Rohit Singh | G299: Male | H299: 37989 | I299: Hyderabad | J299: South | K299: Electronics | L299: Laptop | M299: 11 | N299: 55000 | O299: 5 | P299: 574750 | Q299: 1 | R299: UPI | S299: Ritika | T299: rohit.singh@company.com | U299: 9482699727 | V299: Cancelled
A300: ORD10299 | B300: C007 | C300: P201 | D300: 45935 | E300: 45947 | F300: Arjun Rao | G300: Male | H300: 33726 | I300: Jaipur | J300: North | K300: Home Appliances | L300: Mixer | M300: 12 | N300: 3500 | O300: 0 | P300: 42000 | Q300: 2 | R300: NetBanking | T300: arjun.rao@company.com | U300: 9332473934 | V300: Pending
A301: ORD10300 | B301: C009 | C301: P303 | D301: 46078 | E301: 46089 | F301: Mohit Verma | G301: Male | H301: 37647 | I301: Hyderabad | J301: South | K301: Stationery | L301: Marker | M301: 15 | N301: 45 | O301: 10 | P301: 607.5 | Q301: 2 | R301: Cash | S301: Karan | T301: mohit.verma@company.com | U301: 9647657382 | V301: Pending
A302: ORD10301 | B302: C001 | C302: P303 | D302: 45793 | E302: 45803 | F302: Amit Sharma | G302: Male | H302: 31917 | I302: Bengaluru | J302: South | K302: Stationery | L302: Marker | M302: 13 | N302: 45 | O302: 0 | P302: 585 | Q302: 5 | R302: NetBanking | S302: Rahul | T302: amit.sharma@company.com | U302: 9736797776 | V302: Pending
A303: ORD10302 | B303: C003 | C303: P101 | D303: 46024 | E303: 46027 | F303: Rohit Singh | G303: Male | H303: 27644 | I303: Bengaluru | J303: South | K303: Electronics | L303: Laptop | M303: 8 | N303: 55000 | O303: 0 | P303: 440000 | Q303: 2 | R303: UPI | S303: Karan | T303: rohit.singh@company.com | U303: 9745773533 | V303: Cancelled
A304: ORD10303 | B304: C006 | C304: P101 | D304: 45861 | E304: 45865 | F304: Sneha Joshi | G304: Female | H304: 29443 | I304: Delhi | J304: North | K304: Electronics | L304: Laptop | M304: 4 | N304: 55000 | O304: 20 | P304: 176000 | Q304: 5 | R304: Cash | S304: Rahul | T304: sneha.joshi@company.com | U304: 9246715757 | V304: Pending
A305: ORD10304 | B305: C008 | C305: P201 | D305: 46135 | E305: 46138 | F305: Kavya Nair | G305: Female | H305: 32605 | I305: Ahmedabad | J305: West | K305: Home Appliances | L305: Mixer | M305: 19 | N305: 3500 | O305: 5 | P305: 63175 | Q305: 1 | R305: Card | S305: Neha | T305: kavya.nair@company.com | U305: 9904065774 | V305: Completed
A306: ORD10305 | B306: C005 | C306: P103 | D306: 45718 | E306: 45722 | F306: Vikas Mehta | G306: Male | H306: 36027 | I306: Jaipur | J306: North | K306: Electronics | L306: Keyboard | M306: 17 | N306: 1200 | O306: 15 | P306: 17340 | Q306: 2 | R306: NetBanking | S306: Rahul | T306: vikas.mehta@company.com | U306: 9652985385 | V306: Completed
A307: ORD10306 | B307: C008 | C307: P202 | D307: 46062 | E307: 46070 | F307: Kavya Nair | G307: Female | H307: 36984 | I307: Hyderabad | J307: South | K307: Home Appliances | L307: Iron | M307: 8 | N307: 2200 | O307: 5 | P307: 16720 | Q307: 3 | R307: Card | S307: Neha | T307: kavya.nair@company.com | U307: 9427001508 | V307: Pending
A308: ORD10307 | B308: C006 | C308: P102 | D308: 45704 | E308: 45714 | F308: Sneha Joshi | G308: Female | H308: 33668 | I308: Mumbai | J308: West | K308: Electronics | L308: Mouse | M308: 17 | N308: 700 | O308: 20 | P308: 9520 | Q308: 4 | R308: NetBanking | S308: Neha | T308: sneha.joshi@company.com | U308: 9666803655 | V308: Completed
A309: ORD10308 | B309: C006 | C309: P203 | D309: 45897 | E309: 45908 | F309: Sneha Joshi | G309: Female | H309: 28122 | I309: Pune | J309: West | K309: Home Appliances | L309: Microwave | M309: 6 | N309: 8500 | O309: 15 | P309: 43350 | Q309: 1 | R309: Cash | S309: Aisha | T309: sneha.joshi@company.com | U309: 9134878547 | V309: Completed
A310: ORD10309 | B310: C010 | C310: P201 | D310: 45936 | E310: 45941 | F310: Pooja Shah | G310: Female | H310: 31659 | I310: Hyderabad | J310: South | K310: Home Appliances | L310: Mixer | M310: 3 | N310: 3500 | O310: 10 | P310: 9450 | Q310: 1 | R310: NetBanking | S310: Rahul | T310: pooja.shah@company.com | U310: 9253593557 | V310: Completed
A311: ORD10310 | B311: C009 | C311: P104 | D311: 45674 | E311: 45686 | F311: Mohit Verma | G311: Male | H311: 32734 | I311: Ahmedabad | J311: West | K311: Electronics | L311: Monitor | M311: 2 | N311: 12000 | O311: 20 | P311: 19200 | Q311: 1 | R311: Card | S311: Aisha | T311: mohit.verma@company.com | U311: 9183094051 | V311: Completed
A312: ORD10311 | B312: C005 | C312: P302 | D312: 45943 | E312: 45946 | F312: Vikas Mehta | G312: Male | H312: 33299 | I312: Delhi | J312: North | K312: Stationery | L312: Pen | M312: 12 | N312: 20 | O312: 20 | P312: 192 | Q312: 2 | R312: Card | S312: Rahul | T312: vikas.mehta@company.com | U312: 9293147620 | V312: Completed
... A357: ORD10356 | B357: C008 | C357: P303 | D357: 45941 | E357: 45951 | F357: Kavya Nair | G357: Female | H357: 33746 | I357: Jaipur | J357: North | K357: Stationery | L357: Marker | M357: 5 | N357: 45 | O357: 5 | P357: 213.75 | Q357: 1 | R357: Card | S357: Neha | T357: kavya.nair@company.com | U357: 9810433484 | V357: Completed
A358: ORD10357 | B358: C006 | C358: P102 | D358: \ | E358: 45699 | F358: Sneha Joshi | G358: Female | H358: 32822 | I358: Mumbai | J358: West | K358: Electronics | L358: Mouse | M358: 3 | N358: 700 | O358: 15 | P358: 1785 | Q358: 4 | R358: Cash | S358: Karan | T358: sneha.joshi@company.com | U358: 9990243436 | V358: Completed
A359: ORD10358 | B359: C009 | C359: P203 | D359: 46005 | E359: 46017 | F359: Mohit Verma | G359: Male | H359: 29467 | I359: Jaipur | J359: North | K359: Home Appliances | L359: Microwave | M359: 12 | N359: 8500 | O359: 5 | P359: 96900 | Q359: 3 | R359: Card | S359: Aisha | T359: mohit.verma@company.com | U359: 9396678031 | V359: Pending
A360: ORD10359 | B360: C006 | C360: P203 | D360: 46123 | E360: 46131 | F360: Sneha Joshi | G360: Female | H360: 28920 | I360: Pune | J360: West | K360: Home Appliances | L360: Microwave | M360: 4 | N360: 8500 | O360: 15 | P360: 28900 | Q360: 4 | R360: NetBanking | S360: Aisha | T360: sneha.joshi@company.com | U360: 9818591245 | V360: Pending
A361: ORD10360 | B361: C003 | C361: P302 | D361: 45766 | E361: 45769 | F361: Rohit Singh | G361: Male | H361: 35312 | I361: Jaipur | J361: North | K361: Stationery | L361: Pen | M361: 16 | N361: 20 | O361: 10 | P361: 288 | Q361: 4 | R361: Cash | S361: Neha | T361: rohit.singh@company.com | U361: 9505550047 | V361: Cancelled
A362: ORD10361 | B362: C003 | C362: P301 | D362: 46152 | E362: 46160 | F362: Rohit Singh | G362: Male | H362: 36233 | I362: Mumbai | J362: West | K362: Stationery | L362: Notebook | M362: 3 | N362: 60 | O362: 20 | P362: 144 | Q362: 4 | R362: UPI | S362: Karan | T362: rohit.singh@company.com | U362: 9469828772 | V362: Pending
A363: ORD10362 | B363: C009 | C363: P202 | D363: 45858 | E363: 45864 | F363: Mohit Verma | G363: Male | H363: 30958 | I363: Mumbai | J363: West | K363: Home Appliances | L363: Iron | M363: 19 | N363: 2200 | O363: 10 | P363: 37620 | Q363: 2 | R363: Cash | S363: Karan | T363: mohit.verma@company.com | U363: 9885092680 | V363: Pending
A364: ORD10363 | B364: C009 | C364: P103 | D364: 46045 | E364: 46049 | F364: Mohit Verma | G364: Male | H364: 30872 | I364: Hyderabad | J364: South | K364: Electronics | L364: Keyboard | M364: 7 | N364: 1200 | O364: 20 | P364: 6720 | Q364: 3 | R364: Card | S364: Neha | T364: mohit.verma@company.com | U364: 9362319457 | V364: Cancelled
A365: ORD10364 | B365: C010 | C365: P302 | D365: 46097 | E365: 46102 | F365: Pooja Shah | G365: Female | H365: 32577 | I365: Bengaluru | J365: South | K365: Stationery | L365: Pen | M365: 20 | N365: 20 | O365: 20 | P365: 320 | Q365: 5 | R365: Card | S365: Neha | T365: pooja.shah@company.com | U365: 9223945130 | V365: Pending
A366: ORD10365 | B366: C002 | C366: P103 | D366: 45777 | E366: 45784 | F366: Priya Patel | G366: Female | H366: 31156 | I366: Hyderabad | J366: South | K366: Electronics | L366: Keyboard | M366: 19 | N366: 1200 | O366: 5 | P366: 21660 | Q366: 3 | R366: Card | S366: Ritika | T366: priya.patel@company.com | U366: 9910804926 | V366: Pending
A367: ORD10366 | B367: C010 | C367: P302 | D367: 45691 | E367: 45701 | F367: Pooja Shah | G367: Female | H367: 37846 | I367: Hyderabad | J367: South | K367: Stationery | L367: Pen | M367: 5 | N367: 20 | O367: 0 | P367: 100 | Q367: 2 | R367: UPI | S367: Rahul | T367: pooja.shah@company.com | U367: 9274269744 | V367: Pending
A368: ORD10367 | B368: C002 | C368: P303 | D368: 46088 | E368: 46097 | F368: Priya Patel | G368: Female | H368: 30570 | I368: Jaipur | J368: North | K368: Stationery | L368: Marker | M368: 16 | N368: 45 | O368: 15 | P368: 612 | Q368: 5 | R368: Cash | S368: Aisha | T368: priya.patel@company.com | U368: 9223196101 | V368: Cancelled
A369: ORD10368 | B369: C008 | C369: P202 | D369: 45780 | E369: 45792 | F369: Kavya Nair | G369: Female | H369: 27922 | I369: Jaipur | J369: North | K369: Home Appliances | L369: Iron | M369: 1 | N369: 2200 | O369: 10 | P369: 1980 | Q369: 5 | R369: Card | S369: Rahul | T369: kavya.nair@company.com | U369: 9888477457 | V369: Completed
A370: ORD10369 | B370: C010 | C370: P301 | D370: 46113 | E370: 46117 | F370: Pooja Shah | G370: Female | H370: 31781 | I370: Hyderabad | J370: South | K370: Stationery | L370: Notebook | M370: 19 | N370: 60 | O370: 15 | P370: 969 | Q370: 4 | R370: NetBanking | S370: Neha | T370: pooja.shah@company.com | U370: 9435947486 | V370: Cancelled
A371: ORD10370 | B371: C001 | C371: P101 | E371: 45690 | F371: Amit Sharma | G371: Male | H371: 33738 | I371: Delhi | J371: North | K371: Electronics | L371: Laptop | M371: 15 | N371: 55000 | O371: 0 | P371: 825000 | Q371: 5 | R371: Card | S371: Neha | T371: amit.sharma@company.com | U371: 9411668831 | V371: Cancelled
A372: ORD10371 | B372: C009 | C372: P303 | D372: 45936 | E372: 45938 | F372: Mohit Verma | G372: Male | H372: 32631 | I372: Bengaluru | J372: South | K372: Stationery | L372: Marker | M372: 11 | N372: 45 | O372: 5 | P372: 470.25 | Q372: 5 | R372: NetBanking | S372: Karan | T372: mohit.verma@company.com | U372: 9523682403 | V372: Completed
A373: ORD10372 | B373: C006 | C373: P302 | D373: 45820 | E373: 45825 | F373: Sneha Joshi | G373: Female | H373: 33226 | I373: Jaipur | J373: North | K373: Stationery | L373: Pen | M373: 9 | N373: 20 | O373: 10 | P373: 162 | Q373: 1 | R373: Card | S373: Rahul | T373: sneha.joshi@company.com | U373: 9652936744 | V373: Cancelled
A374: ORD10373 | B374: C004 | C374: P303 | D374: 45979 | E374: 45981 | F374: Anita Gupta | G374: Female | H374: 34889 | I374: Bengaluru | J374: South | K374: Stationery | L374: Marker | M374: 5 | N374: 45 | O374: 5 | P374: 213.75 | Q374: 3 | R374: Card | S374: Neha | T374: anita.gupta@company.com | U374: 9726464733 | V374: Pending
A375: ORD10374 | B375: C007 | C375: P102 | D375: 45962 | E375: 45963 | F375: Arjun Rao | G375: Male | H375: 36152 | I375: Hyderabad | J375: South | K375: Electronics | L375: Mouse | M375: 5 | N375: 700 | O375: 10 | P375: 3150 | Q375: 2 | R375: UPI | S375: Rahul | T375: arjun.rao@company.com | U375: 9273520544 | V375: Completed
A376: ORD10375 | B376: C005 | C376: P102 | D376: 45681 | E376: 45688 | F376: Vikas Mehta | G376: Male | H376: 29212 | I376: Kolkata | J376: East | K376: Electronics | L376: Mouse | M376: 1 | N376: 700 | O376: 0 | P376: 700 | Q376: 1 | R376: UPI | S376: Karan | T376: vikas.mehta@company.com | U376: 9374259988 | V376: Completed
A377: ORD10376 | B377: C008 | C377: P102 | D377: 46066 | E377: 46074 | F377: Kavya Nair | G377: Female | H377: 27743 | I377: Mumbai | J377: West | K377: Electronics | L377: Mouse | M377: 13 | N377: 700 | O377: 20 | P377: 7280 | Q377: 2 | R377: Card | S377: Ritika | T377: kavya.nair@company.com | U377: 9538129419 | V377: Completed
A378: ORD10377 | B378: C009 | C378: P104 | D378: 45696 | E378: 45707 | F378: Mohit Verma | G378: Male | H378: 34106 | I378: Pune | J378: West | K378: Electronics | L378: Monitor | M378: 20 | N378: 12000 | O378: 0 | P378: 240000 | Q378: 2 | R378: Card | S378: Neha | T378: mohit.verma@company.com | U378: 9382815686 | V378: Completed
A379: ORD10378 | B379: C007 | C379: P103 | D379: 46019 | E379: 46028 | F379: Arjun Rao | G379: Male | H379: 28020 | I379: Kolkata | J379: East | K379: Electronics | L379: Keyboard | M379: 9 | N379: 1200 | O379: 15 | P379: 9180 | Q379: 1 | R379: UPI | S379: Ritika | T379: arjun.rao@company.com | U379: 9450746157 | V379: Pending
A380: ORD10379 | B380: C007 | C380: P302 | D380: 45931 | E380: 45933 | F380: Arjun Rao | G380: Male | H380: 35421 | I380: Jaipur | J380: North | K380: Stationery | L380: Pen | M380: 3 | N380: 20 | O380: 15 | P380: 51 | Q380: 3 | R380: Cash | S380: Neha | T380: arjun.rao@company.com | U380: 9349012570 | V380: Pending
...

Sheet Product_Master
A1: Product_ID | B1: Product_Name | C1: Category | D1: Supplier | E1: Cost_Price | F1: Warranty_Months
A2: P101 | B2: Laptop | C2: Electronics | D2: TechHub | E2: 41250 | F2: 12
A3: P102 | B3: Mouse | C3: Electronics | D3: TechHub | E3: 525 | F3: 24
A4: P103 | B4: Keyboard | C4: Electronics | D4: TechHub | E4: 900 | F4: 6
A5: P104 | B5: Monitor | C5: Electronics | D5: Global Trade | E5: 9000 | F5: 24
A6: P201 | B6: Mixer | C6: Home Appliances | D6: Global Trade | E6: 2625 | F6: 6
A7: P202 | B7: Iron | C7: Home Appliances | D7: Global Trade | E7: 1650 | F7: 24
A8: P203 | B8: Microwave | C8: Home Appliances | D8: TechHub | E8: 6375 | F8: 24
A9: P301 | B9: Notebook | C9: Stationery | D9: ABC Corp | E9: 45 | F9: 12
A10: P302 | B10: Pen | C10: Stationery | D10: Prime Supplies | E10: 15 | F10: 12
A11: P303 | B11: Marker | C11: Stationery | D11: TechHub | E11: 33.75 | F11: 12

Sheet Customer_Master
A1: Customer_ID | B1: Customer_Name | C1: Membership | D1: State
A2: C001 | B2: Amit Sharma | C2: Silver | D2: RJ
A3: C002 | B3: Priya Patel | C3: Platinum | D3: WB
A4: C003 | B4: Rohit Singh | C4: Gold | D4: DL
A5: C004 | B5: Anita Gupta | C5: Gold | D5: WB
A6: C005 | B6: Vikas Mehta | C6: Gold | D6: DL
A7: C006 | B7: Sneha Joshi | C7: Gold | D7: WB
A8: C007 | B8: Arjun Rao | C8: Silver | D8: RJ
A9: C008 | B9: Kavya Nair | C9: Silver | D9: WB
A10: C009 | B10: Mohit Verma | C10: Platinum | D10: KA
A11: C010 | B11: Pooja Shah | C11: Silver | D11: WB

Sheet Q1_Q2_Q3
A1: Customer_Classification | B1: Customer_Name | C1: Customer_Code | D1: Email_Id | E1: Customer_Age | F1: Delivery_Time(Days) | G1: Delivery_Status
A2: =IF(AND(Sales_Data!P2>=100000,Sales_Data!Q2>=4,Sales_Data!V2="Completed",Sales_Data!O2<=10),"Platinum",IF(AND(Sales_Data!P2>=50000,Sales_Data!Q2>=3,Sales_Data!V2="Completed"),"Gold",IF(AND(Sales_Data!P2<50000,Sales_Data!V2="Completed"),"Silver",IF(OR(Sales_Data!Q2<=2,Sales_Data!V2="Canceled"),"Blacklisted","Others")))) -> Silver | B2: =PROPER(TRIM(Sales_Data!F2)) -> Kavya Nair | C2: =LEFT(B2,3)&RIGHT(Sales_Data!B2,3)&LEFT(Sales_Data!I2,2) -> Kav008Hy | D2: =IF(ISNUMBER(SEARCH("@",Sales_Data!T2)),LOWER(Sales_Data!T2),"Invalid_Email") -> kavya.nair@company.com | E2: =DATEDIF(Sales_Data!H2,TODAY(),"Y") -> 50 | F2: =IFERROR(DATEDIF(Sales_Data!D2,Sales_Data!E2,"D"),"Information_Not_Given") -> 4 | G2: {=_xlfn.IFS(F2<=5,"One_Time",F2>5,"Delayed",F2="Information_Not_given","Pending")} -> One_Time
A3: =IF(AND(Sales_Data!P3>=100000,Sales_Data!Q3>=4,Sales_Data!V3="Completed",Sales_Data!O3<=10),"Platinum",IF(AND(Sales_Data!P3>=50000,Sales_Data!Q3>=3,Sales_Data!V3="Completed"),"Gold",IF(AND(Sales_Data!P3<50000,Sales_Data!V3="Completed"),"Silver",IF(OR(Sales_Data!Q3<=2,Sales_Data!V3="Canceled"),"Blacklisted","Others")))) -> Blacklisted | B3: =PROPER(TRIM(Sales_Data!F3)) -> Kavya Nair | C3: =LEFT(B3,3)&RIGHT(Sales_Data!B3,3)&LEFT(Sales_Data!I3,2) -> Kav008De | D3: =IF(ISNUMBER(SEARCH("@",Sales_Data!T3)),LOWER(Sales_Data!T3),"Invalid_Email") -> kavya.nair@company.com | E3: =DATEDIF(Sales_Data!H3,TODAY(),"Y") -> 25 | F3: =IFERROR(DATEDIF(Sales_Data!D3,Sales_Data!E3,"D"),"Information_Not_Given") -> 7 | G3: {=_xlfn.IFS(F3<=5,"One_Time",F3>5,"Delayed",F3="Information_Not_given","Pending")} -> Delayed
A4: =IF(AND(Sales_Data!P4>=100000,Sales_Data!Q4>=4,Sales_Data!V4="Completed",Sales_Data!O4<=10),"Platinum",IF(AND(Sales_Data!P4>=50000,Sales_Data!Q4>=3,Sales_Data!V4="Completed"),"Gold",IF(AND(Sales_Data!P4<50000,Sales_Data!V4="Completed"),"Silver",IF(OR(Sales_Data!Q4<=2,Sales_Data!V4="Canceled"),"Blacklisted","Others")))) -> Others | B4: =PROPER(TRIM(Sales_Data!F4)) -> Pooja Shah | C4: =LEFT(B4,3)&RIGHT(Sales_Data!B4,3)&LEFT(Sales_Data!I4,2) -> Poo010Be | D4: =IF(ISNUMBER(SEARCH("@",Sales_Data!T4)),LOWER(Sales_Data!T4),"Invalid_Email") -> pooja.shah@company.com | E4: =DATEDIF(Sales_Data!H4,TODAY(),"Y") -> 32 | F4: =IFERROR(DATEDIF(Sales_Data!D4,Sales_Data!E4,"D"),"Information_Not_Given") -> 11 | G4: {=_xlfn.IFS(F4<=5,"One_Time",F4>5,"Delayed",F4="Information_Not_given","Pending")} -> Delayed
A5: =IF(AND(Sales_Data!P5>=100000,Sales_Data!Q5>=4,Sales_Data!V5="Completed",Sales_Data!O5<=10),"Platinum",IF(AND(Sales_Data!P5>=50000,Sales_Data!Q5>=3,Sales_Data!V5="Completed"),"Gold",IF(AND(Sales_Data!P5<50000,Sales_Data!V5="Completed"),"Silver",IF(OR(Sales_Data!Q5<=2,Sales_Data!V5="Canceled"),"Blacklisted","Others")))) -> Others | B5: =PROPER(TRIM(Sales_Data!F5)) -> Kavya Nair | C5: =LEFT(B5,3)&RIGHT(Sales_Data!B5,3)&LEFT(Sales_Data!I5,2) -> Kav008Be | D5: =IF(ISNUMBER(SEARCH("@",Sales_Data!T5)),LOWER(Sales_Data!T5),"Invalid_Email") -> kavya.nair@company.com | E5: =DATEDIF(Sales_Data!H5,TODAY(),"Y") -> 22 | F5: =IFERROR(DATEDIF(Sales_Data!D5,Sales_Data!E5,"D"),"Information_Not_Given") -> 12 | G5: {=_xlfn.IFS(F5<=5,"One_Time",F5>5,"Delayed",F5="Information_Not_given","Pending")} -> Delayed
A6: =IF(AND(Sales_Data!P6>=100000,Sales_Data!Q6>=4,Sales_Data!V6="Completed",Sales_Data!O6<=10),"Platinum",IF(AND(Sales_Data!P6>=50000,Sales_Data!Q6>=3,Sales_Data!V6="Completed"),"Gold",IF(AND(Sales_Data!P6<50000,Sales_Data!V6="Completed"),"Silver",IF(OR(Sales_Data!Q6<=2,Sales_Data!V6="Canceled"),"Blacklisted","Others")))) -> Blacklisted | B6: =PROPER(TRIM(Sales_Data!F6)) -> Mohit Verma | C6: =LEFT(B6,3)&RIGHT(Sales_Data!B6,3)&LEFT(Sales_Data!I6,2) -> Moh009De | D6: =IF(ISNUMBER(SEARCH("@",Sales_Data!T6)),LOWER(Sales_Data!T6),"Invalid_Email") -> mohit.verma@company.com | E6: =DATEDIF(Sales_Data!H6,TODAY(),"Y") -> 50 | F6: =IFERROR(DATEDIF(Sales_Data!D6,Sales_Data!E6,"D"),"Information_Not_Given") -> 10 | G6: {=_xlfn.IFS(F6<=5,"One_Time",F6>5,"Delayed",F6="Information_Not_given","Pending")} -> Delayed
A7: =IF(AND(Sales_Data!P7>=100000,Sales_Data!Q7>=4,Sales_Data!V7="Completed",Sales_Data!O7<=10),"Platinum",IF(AND(Sales_Data!P7>=50000,Sales_Data!Q7>=3,Sales_Data!V7="Completed"),"Gold",IF(AND(Sales_Data!P7<50000,Sales_Data!V7="Completed"),"Silver",IF(OR(Sales_Data!Q7<=2,Sales_Data!V7="Canceled"),"Blacklisted","Others")))) -> Silver | B7: =PROPER(TRIM(Sales_Data!F7)) -> Arjun Rao | C7: =LEFT(B7,3)&RIGHT(Sales_Data!B7,3)&LEFT(Sales_Data!I7,2) -> Arj007Hy | D7: =IF(ISNUMBER(SEARCH("@",Sales_Data!T7)),LOWER(Sales_Data!T7),"Invalid_Email") -> arjun.rao@company.com | E7: =DATEDIF(Sales_Data!H7,TODAY(),"Y") -> 38 | F7: =IFERROR(DATEDIF(Sales_Data!D7,Sales_Data!E7,"D"),"Information_Not_Given") -> 8 | G7: {=_xlfn.IFS(F7<=5,"One_Time",F7>5,"Delayed",F7="Information_Not_given","Pending")} -> Delayed
A8: =IF(AND(Sales_Data!P8>=100000,Sales_Data!Q8>=4,Sales_Data!V8="Completed",Sales_Data!O8<=10),"Platinum",IF(AND(Sales_Data!P8>=50000,Sales_Data!Q8>=3,Sales_Data!V8="Completed"),"Gold",IF(AND(Sales_Data!P8<50000,Sales_Data!V8="Completed"),"Silver",IF(OR(Sales_Data!Q8<=2,Sales_Data!V8="Canceled"),"Blacklisted","Others")))) -> Silver | B8: =PROPER(TRIM(Sales_Data!F8)) -> Kavya Nair | C8: =LEFT(B8,3)&RIGHT(Sales_Data!B8,3)&LEFT(Sales_Data!I8,2) -> Kav008Hy | D8: =IF(ISNUMBER(SEARCH("@",Sales_Data!T8)),LOWER(Sales_Data!T8),"Invalid_Email") -> kavya.nair@company.com | E8: =DATEDIF(Sales_Data!H8,TODAY(),"Y") -> 23 | F8: =IFERROR(DATEDIF(Sales_Data!D8,Sales_Data!E8,"D"),"Information_Not_Given") -> Information_Not_Given | G8: {=_xlfn.IFS(F8<=5,"One_Time",F8>5,"Delayed",F8="Information_Not_given","Pending")} -> Delayed
A9: =IF(AND(Sales_Data!P9>=100000,Sales_Data!Q9>=4,Sales_Data!V9="Completed",Sales_Data!O9<=10),"Platinum",IF(AND(Sales_Data!P9>=50000,Sales_Data!Q9>=3,Sales_Data!V9="Completed"),"Gold",IF(AND(Sales_Data!P9<50000,Sales_Data!V9="Completed"),"Silver",IF(OR(Sales_Data!Q9<=2,Sales_Data!V9="Canceled"),"Blacklisted","Others")))) -> Gold | B9: =PROPER(TRIM(Sales_Data!F9)) -> Priya Patel | C9: =LEFT(B9,3)&RIGHT(Sales_Data!B9,3)&LEFT(Sales_Data!I9,2) -> Pri002Mu | D9: =IF(ISNUMBER(SEARCH("@",Sales_Data!T9)),LOWER(Sales_Data!T9),"Invalid_Email") -> priya.patel@company.com | E9: =DATEDIF(Sales_Data!H9,TODAY(),"Y") -> 31 | F9: =IFERROR(DATEDIF(Sales_Data!D9,Sales_Data!E9,"D"),"Information_Not_Given") -> 6 | G9: {=_xlfn.IFS(F9<=5,"One_Time",F9>5,"Delayed",F9="Information_Not_given","Pending")} -> Delayed
A10: =IF(AND(Sales_Data!P10>=100000,Sales_Data!Q10>=4,Sales_Data!V10="Completed",Sales_Data!O10<=10),"Platinum",IF(AND(Sales_Data!P10>=50000,Sales_Data!Q10>=3,Sales_Data!V10="Completed"),"Gold",IF(AND(Sales_Data!P10<50000,Sales_Data!V10="Completed"),"Silver",IF(OR(Sales_Data!Q10<=2,Sales_Data!V10="Canceled"),"Blacklisted","Others")))) -> Silver | B10: =PROPER(TRIM(Sales_Data!F10)) -> Kavya Nair | C10: =LEFT(B10,3)&RIGHT(Sales_Data!B10,3)&LEFT(Sales_Data!I10,2) -> Kav008Pu | D10: =IF(ISNUMBER(SEARCH("@",Sales_Data!T10)),LOWER(Sales_Data!T10),"Invalid_Email") -> kavya.nair@company.com | E10: =DATEDIF(Sales_Data!H10,TODAY(),"Y") -> 29 | F10: =IFERROR(DATEDIF(Sales_Data!D10,Sales_Data!E10,"D"),"Information_Not_Given") -> 2 | G10: {=_xlfn.IFS(F10<=5,"One_Time",F10>5,"Delayed",F10="Information_Not_given","Pending")} -> One_Time
A11: =IF(AND(Sales_Data!P11>=100000,Sales_Data!Q11>=4,Sales_Data!V11="Completed",Sales_Data!O11<=10),"Platinum",IF(AND(Sales_Data!P11>=50000,Sales_Data!Q11>=3,Sales_Data!V11="Completed"),"Gold",IF(AND(Sales_Data!P11<50000,Sales_Data!V11="Completed"),"Silver",IF(OR(Sales_Data!Q11<=2,Sales_Data!V11="Canceled"),"Blacklisted","Others")))) -> Silver | B11: =PROPER(TRIM(Sales_Data!F11)) -> Priya Patel | C11: =LEFT(B11,3)&RIGHT(Sales_Data!B11,3)&LEFT(Sales_Data!I11,2) -> Pri002Mu | D11: =IF(ISNUMBER(SEARCH("@",Sales_Data!T11)),LOWER(Sales_Data!T11),"Invalid_Email") -> priya.patel@company.com | E11: =DATEDIF(Sales_Data!H11,TODAY(),"Y") -> 36 | F11: =IFERROR(DATEDIF(Sales_Data!D11,Sales_Data!E11,"D"),"Information_Not_Given") -> 2 | G11: {=_xlfn.IFS(F11<=5,"One_Time",F11>5,"Delayed",F11="Information_Not_given","Pending")} -> One_Time
A12: =IF(AND(Sales_Data!P12>=100000,Sales_Data!Q12>=4,Sales_Data!V12="Completed",Sales_Data!O12<=10),"Platinum",IF(AND(Sales_Data!P12>=50000,Sales_Data!Q12>=3,Sales_Data!V12="Completed"),"Gold",IF(AND(Sales_Data!P12<50000,Sales_Data!V12="Completed"),"Silver",IF(OR(Sales_Data!Q12<=2,Sales_Data!V12="Canceled"),"Blacklisted","Others")))) -> Blacklisted | B12: =PROPER(TRIM(Sales_Data!F12)) -> Rohit Singh | C12: =LEFT(B12,3)&RIGHT(Sales_Data!B12,3)&LEFT(Sales_Data!I12,2) -> Roh003De | D12: =IF(ISNUMBER(SEARCH("@",Sales_Data!T12)),LOWER(Sales_Data!T12),"Invalid_Email") -> rohit.singh@company.com | E12: =DATEDIF(Sales_Data!H12,TODAY(),"Y") -> 44 | F12: =IFERROR(DATEDIF(Sales_Data!D12,Sales_Data!E12,"D"),"Information_Not_Given") -> 4 | G12: {=_xlfn.IFS(F12<=5,"One_Time",F12>5,"Delayed",F12="Information_Not_given","Pending")} -> One_Time
A13: =IF(AND(Sales_Data!P13>=100000,Sales_Data!Q13>=4,Sales_Data!V13="Completed",Sales_Data!O13<=10),"Platinum",IF(AND(Sales_Data!P13>=50000,Sales_Data!Q13>=3,Sales_Data!V13="Completed"),"Gold",IF(AND(Sales_Data!P13<50000,Sales_Data!V13="Completed"),"Silver",IF(OR(Sales_Data!Q13<=2,Sales_Data!V13="Canceled"),"Blacklisted","Others")))) -> Others | B13: =PROPER(TRIM(Sales_Data!F13)) -> Kavya Nair | C13: =LEFT(B13,3)&RIGHT(Sales_Data!B13,3)&LEFT(Sales_Data!I13,2) -> Kav008Ah | D13: =IF(ISNUMBER(SEARCH("@",Sales_Data!T13)),LOWER(Sales_Data!T13),"Invalid_Email") -> kavya.nair@company.com | E13: =DATEDIF(Sales_Data!H13,TODAY(),"Y") -> 44 | F13: =IFERROR(DATEDIF(Sales_Data!D13,Sales_Data!E13,"D"),"Information_Not_Given") -> 7 | G13: {=_xlfn.IFS(F13<=5,"One_Time",F13>5,"Delayed",F13="Information_Not_given","Pending")} -> Delayed
... A501: =IF(AND(Sales_Data!P501>=100000,Sales_Data!Q501>=4,Sales_Data!V501="Completed",Sales_Data!O501<=10),"Platinum",IF(AND(Sales_Data!P501>=50000,Sales_Data!Q501>=3,Sales_Data!V501="Completed"),"Gold",IF(AND(Sales_Data!P501<50000,Sales_Data!V501="Completed"),"Silver",IF(OR(Sales_Data!Q501<=2,Sales_Data!V501="Canceled"),"Blacklisted","Others")))) -> Blacklisted | B501: =PROPER(TRIM(Sales_Data!F501)) -> Priya Patel | C501: =LEFT(B501,3)&RIGHT(Sales_Data!B501,3)&LEFT(Sales_Data!I501,2) -> Pri002Be | D501: =IF(ISNUMBER(SEARCH("@",Sales_Data!T501)),LOWER(Sales_Data!T501),"Invalid_Email") -> priya.patel@company.com | E501: =DATEDIF(Sales_Data!H501,TODAY(),"Y") -> 49 | F501: =IFERROR(DATEDIF(Sales_Data!D501,Sales_Data!E501,"D"),"Information_Not_Given") -> 7 | G501: {=_xlfn.IFS(F501<=5,"One_Time",F501>5,"Delayed",F501="Information_Not_given","Pending")} -> Delayed

Sheet Q4_Product_Lookup_Report
A1: Product_Id | B1: Product_Name | C1: Category | D1: Supplier | E1: Cost_Price | F1: Warranty(Months)
A2: P302 | B2: {=IFERROR(VLOOKUP(A2,Corporate_sales_data_xlsx___Product_master[],{2,3,4,5,6},FALSE),"Product Not Found")} -> Pen | C2: Stationery | D2: Prime Supplies | E2: 15 | F2: 12

Sheet Q5_Sales_Summary_Report
A1: Total_Sales_Amount_for_Electronics&Completed | B1: =SUMIFS(Sales_Data!P:P,Sales_Data!K:K,"Electronics",Sales_Data!V:V,"Completed") -> 7222090
A2: Total_Sales_Amount_by_Neha&NorthRegion | B2: =SUMIFS(Sales_Data!P:P,Sales_Data!S:S,"Neha",Sales_Data!J:J,"North") -> 1550369.2
A3: Number_of_Orders_where_dis(>=15%)&UPI | B3: =COUNTIFS(Sales_Data!O:O,">=15",Sales_Data!R:R,"UPI") -> 45
A4: Number_of_Customers_give_Rating(5)&Completed | B4: =COUNTIFS(Sales_Data!Q:Q,"=5",Sales_Data!V:V,"Completed") -> 27
A5: Average_Sales_Amount_West&Rating(>5) | B5: =SUMIFS(Sales_Data!P:P,Sales_Data!J:J,"West",Sales_Data!M:M,">5") -> 12589316

Sheet Q6_Sales_Statistics_Report
A1: Average_Sales_Amount | B1: =AVERAGE(Sales_Data!P:P) -> 69531.875
A2: Median_Sales_Amount | B2: =MEDIAN(Sales_Data!P:P) -> 10475
A3: Highest_Sales_Amount | B3: =MAX(Sales_Data!P:P) -> 1045000
A4: Lowest_Sales_Amount | B4: =MIN(Sales_Data!P:P) -> 19
A5: StDev_of_the_Sales_Amount | B5: =_xlfn.STDEV.P(Sales_Data!P:P) -> 166984.21
A6: 90th%_of_the_Sales_Amount | B6: =_xlfn.PERCENTILE.INC(Sales_Data!P:P,0.9) -> 163880

Sheet Q7_Product_Performance_Report
A1: Total_Revenue-Generated | B1: =SUMPRODUCT(Sales_Data!M:M,Sales_Data!N:N) -> 36610875
A2: Weighted_Average | B2: =SUMPRODUCT(Sales_Data!M:M,Sales_Data!N:N)/SUM(Sales_Data!M:M) -> 6990.8106
A3: Total_Value_in_the_Sales_Column | B3: =SUM(Sales_Data!P:P) -> 34765938
A4: Total_Discounted_Amount | B4: =SUMPRODUCT(Sales_Data!M:M,Sales_Data!N:N,Sales_Data!O:O)/100 -> 2918151.5

Sheet Q8_Financial_Analysis_Report
A1: Plan | B1: Amount
A2: Future_Value | B2: =ROUND(FV(10%/12,5*12,-50000),2) -> 3871853.6
A3: Monthly_Investment | B3: =-PMT(10%/12,5*12,0,5000000) -> 64568.557
A4: Monthly_EMІ | B4: =ROUND(PMT(9%/12,5*12,-1000000),0) -> 20758

Sheet Q9_Cleaned_Data
A1: Order_ID | B1: Customer_ID | C1: Product_ID | D1: Order_Date | E1: Delivery_Date | F1: Customer_Name | G1: Gender | H1: DOB | I1: City | J1: Region | K1: Category | L1: Product_Name | M1: Quantity | N1: Unit_Price | O1: Discount_% | P1: Sales | Q1: Rating | R1: Payment_Mode | S1: Salesperson | T1: Email | U1: Phone | V1: Order_Status
A2: ORD10001 | B2: C008 | C2: P202 | D2: 45918 | E2: 45922 | F2: Kavya Nair | G2: Female | H2: 27973 | I2: Hyderabad | J2: South | K2: Home Appliances | L2: Iron | M2: 4 | N2: 2200 | O2: 10 | P2: 7920 | Q2: 4 | R2: Cash | S2: Ritika | T2: KAvya.nair@company.com | U2: 9431429797 | V2: Completed
A3: ORD10002 | B3: C008 | C3: P104 | D3: 45774 | E3: 45781 | F3: Kavya Nair | G3: Female | H3: 36815 | I3: Delhi | J3: North | K3: Electronics | L3: Monitor | M3: 17 | N3: 12000 | O3: 10 | P3: 183600 | Q3: 1 | R3: NetBanking | S3: Rahul | T3: kavya.nair@company.com | U3: 9129865339 | V3: Completed
A4: ORD10003 | B4: C010 | C4: P101 | D4: 45903 | E4: 45914 | F4: Pooja Shah | G4: Female | H4: 34593 | I4: Bengaluru | J4: South | K4: Electronics | L4: Laptop | M4: 5 | N4: 55000 | O4: 5 | P4: 261250 | Q4: 3 | R4: NetBanking | S4: Aisha | T4: pooja.shah@company.com | U4: 9380975626 | V4: Pending
A5: ORD10005 | B5: C009 | C5: P103 | D5: 45927 | E5: 45937 | F5: Mohit Verma | G5: Male | H5: 27863 | I5: Delhi | J5: North | K5: Electronics | L5: Keyboard | M5: 8 | N5: 1200 | O5: 5 | P5: 9120 | Q5: 2 | R5: Card | S5: Aisha | T5: mohit.verma@company.com | U5: 9724635978 | V5: Pending
A6: ORD10006 | B6: C007 | C6: P202 | D6: 46026 | E6: 46034 | F6: Arjun Rao | G6: Male | H6: 32180 | I6: Hyderabad | J6: South | K6: Home Appliances | L6: Iron | M6: 4 | N6: 2200 | O6: 0 | P6: 8800 | Q6: 1 | R6: UPI | S6: Ritika | T6: arjun.rao@company.com | U6: 9780584905 | V6: Completed
A7: ORD10007 | B7: C008 | C7: P201 | D7: 45710 | E7: 46078 | F7: Kavya Nair | G7: Female | H7: 37700 | I7: Hyderabad | J7: South | K7: Home Appliances | L7: Mixer | M7: 2 | N7: 3500 | O7: 5 | P7: 6650 | Q7: 1 | R7: UPI | S7: Ritika | T7: kavya.nair@company.com | U7: 9958252176 | V7: Completed
A8: ORD10008 | B8: C002 | C8: P104 | D8: 45760 | E8: 45766 | F8: Priya Patel | G8: Female | H8: 34765 | I8: Mumbai | J8: West | K8: Electronics | L8: Monitor | M8: 14 | N8: 12000 | O8: 15 | P8: 142800 | Q8: 4 | R8: NetBanking | S8: Ritika | T8: priYa.patel@company.com | U8: 9705521654 | V8: Completed
A9: ORD10009 | B9: C008 | C9: P104 | D9: 46053 | E9: 46055 | F9: Kavya Nair | G9: Female | H9: 35526 | I9: Pune | J9: West | K9: Electronics | L9: Monitor | M9: 4 | N9: 12000 | O9: 15 | P9: 40800 | Q9: 4 | R9: UPI | S9: Neha | T9: kavya.nair@company.com | U9: 9588041011 | V9: Completed
A10: ORD10010 | B10: C002 | C10: P301 | D10: 45741 | E10: 45743 | F10: Priya Patel | G10: Female | H10: 32880 | I10: Mumbai | J10: West | K10: Stationery | L10: Notebook | M10: 6 | N10: 60 | O10: 0 | P10: 360 | Q10: 4 | R10: Card | S10: Neha | T10: PRiya.patel@company.com | U10: 9340540608 | V10: Completed
A11: ORD10011 | B11: C003 | C11: P202 | D11: 45919 | E11: 45923 | F11: Rohit Singh | G11: Male | H11: 30081 | I11: Delhi | J11: North | K11: Home Appliances | L11: Iron | M11: -3 | N11: 2200 | O11: 0 | P11: 35200 | Q11: 2 | R11: Card | S11: Rahul | T11: rohit.singh@company.com | U11: 9521710321 | V11: Pending
A12: ORD10012 | B12: C008 | C12: P201 | D12: 45724 | E12: 45731 | F12: Kavya Nair | G12: Female | H12: 29974 | I12: Ahmedabad | J12: West | K12: Home Appliances | L12: Mixer | M12: 10 | N12: 3500 | O12: 5 | P12: 33250 | Q12: 5 | R12: Card | S12: Aisha | T12: kavya.nair@company.com | U12: 9123535241 | V12: Cancelled
A13: ORD10013 | B13: C002 | C13: P202 | D13: 45667 | E13: 45672 | F13: Priya Patel | G13: Female | H13: 33791 | I13: Pune | J13: West | K13: Home Appliances | L13: Iron | M13: 15 | N13: 2200 | O13: 10 | P13: 29700 | Q13: 1 | R13: UPI | S13: Neha | T13: priya.patel@company.com | U13: 9367316892 | V13: Pending
... A48: ORD10048 | B48: C006 | C48: P102 | D48: 45988 | E48: 45994 | F48: Sneha Joshi | G48: Female | H48: 36125 | I48: Jaipur | J48: North | K48: Electronics | L48: Mouse | M48: 19 | N48: 700 | O48: 20 | P48: 10640 | Q48: 1 | R48: Cash | S48: Neha | T48: sneha.joshi@company.com | U48: 9238141322 | V48: Completed
A49: ORD10049 | B49: C009 | C49: P104 | D49: 46131 | E49: Pending | F49: Mohit Verma | G49: Male | H49: 35219 | I49: Delhi | J49: North | K49: Electronics | L49: Monitor | M49: 19 | N49: 12000 | O49: 0 | P49: 228000 | Q49: 1 | R49: NetBanking | S49: Aisha | T49: mohit.verma@company.com | U49: 9890380030 | V49: Completed
A50: ORD10050 | B50: C004 | C50: P103 | D50: 46131 | E50: 46133 | F50: Anita Gupta | G50: Female | H50: 31851 | I50: Pune | J50: West | K50: Electronics | L50: Keyboard | M50: 6 | N50: 1200 | O50: 5 | P50: 6840 | Q50: 2 | R50: Cash | S50: Ritika | T50: anita.gupta@company.com | U50: 9495893170 | V50: Pending
A51: ORD10051 | B51: C010 | C51: P202 | D51: 45744 | E51: 45754 | F51: Pooja Shah | G51: Female | H51: 28906 | I51: Bengaluru | J51: South | K51: Home Appliances | L51: Iron | M51: 7 | N51: 2200 | O51: 15 | P51: 13090 | Q51: 1 | R51: UPI | S51: Aisha | T51: pooja.shah@company.com | U51: 9485166307 | V51: Completed
A52: ORD10052 | B52: C002 | C52: P301 | D52: 45894 | E52: 45897 | F52: Priya Patel | G52: Female | H52: 36747 | I52: Jaipur | J52: North | K52: Stationery | L52: Notebook | M52: 8 | N52: 60 | O52: 10 | P52: 432 | Q52: 5 | R52: Card | S52: Aisha | T52: priya.patel@company.com | U52: 9924709648 | V52: Cancelled
A53: ORD10053 | B53: C005 | C53: P101 | D53: 45888 | E53: 45892 | F53: Vikas Mehta | G53: Male | H53: 27776 | I53: Kolkata | J53: East | K53: Electronics | L53: Laptop | M53: 12 | N53: 55000 | O53: 5 | P53: 627000 | Q53: 2 | R53: UPI | S53: Rahul | T53: vikas.mehta@company.com | U53: 9350554626 | V53: Pending
A54: ORD10054 | B54: C008 | C54: P102 | D54: 45865 | E54: 45874 | F54: Kavya Nair | G54: Female | H54: 27488 | I54: Jaipur | J54: North | K54: Electronics | L54: Mouse | M54: 3 | N54: 700 | O54: 0 | P54: 2100 | Q54: 3 | R54: Card | S54: Karan | T54: kavya.nair@company.com | U54: 9743295580 | V54: Cancelled
A55: ORD10055 | B55: C003 | C55: P301 | D55: 45709 | E55: 45714 | F55: Rohit Singh | G55: Male | H55: 28105 | I55: Ahmedabad | J55: West | K55: Stationery | L55: Notebook | M55: 19 | N55: 60 | O55: 15 | P55: 969 | Q55: 4 | R55: Card | S55: Rahul | T55: rohit.singh@company.com | U55: 9822926495 | V55: Cancelled
A56: ORD10056 | B56: C001 | C56: P301 | D56: 45879 | E56: 45880 | F56: Amit Sharma | G56: Male | H56: 29192 | I56: Jaipur | J56: North | K56: Stationery | L56: Notebook | M56: 9 | N56: 60 | O56: 20 | P56: 432 | Q56: 1 | R56: NetBanking | S56: Neha | T56: amit.sharma@company.com | U56: 9518298190 | V56: Pending
A57: ORD10057 | B57: C001 | C57: P102 | D57: 46105 | E57: 46111 | F57: Amit Sharma | G57: Male | H57: 28851 | I57: Bengaluru | J57: South | K57: Electronics | L57: Mouse | M57: 6 | N57: 700 | O57: 0 | P57: 4200 | Q57: 4 | R57: UPI | S57: Rahul | T57: amit.sharmcompany.com | U57: 9366223547 | V57: Cancelled
A58: ORD10058 | B58: C003 | C58: P303 | D58: 46094 | E58: 46100 | F58: Rohit Singh | G58: Male | H58: 27499 | I58: Delhi | J58: North | K58: Stationery | L58: Marker | M58: 18 | N58: 45 | O58: 5 | P58: 769.5 | Q58: 1 | R58: Card | S58: Aisha | T58: rohit.singh@company.com | U58: 9701988524 | V58: Pending
A59: ORD10059 | B59: C007 | C59: P302 | D59: 45823 | E59: 45834 | F59: Arjun Rao | G59: Male | H59: 32496 | I59: Jaipur | J59: North | K59: Stationery | L59: Pen | M59: 8 | N59: 20 | O59: 5 | P59: 152 | Q59: 1 | R59: Card | S59: Ritika | T59: arjun.rao@company.com | U59: 9836327649 | V59: completed
A60: ORD10060 | B60: C005 | C60: P102 | D60: 45721 | E60: 45722 | F60: Vikas Mehta | G60: Male | H60: 28921 | I60: Jaipur | J60: North | K60: Electronics | L60: Mouse | M60: 8 | N60: 700 | O60: 10 | P60: 5040 | Q60: 1 | R60: NetBanking | S60: Aisha | T60: Vikas.mehta@company.com | U60: 9261800516 | V60: Cancelled
A61: ORD10061 | B61: C008 | C61: P302 | D61: 46121 | E61: 46131 | F61: Kavya Nair | G61: Female | H61: 37972 | I61: Delhi | J61: North | K61: Stationery | L61: Pen | M61: 7 | N61: 20 | O61: 15 | P61: 119 | Q61: 5 | R61: Card | S61: Rahul | T61: kavya.nair@company.com | U61: 9950802015 | V61: Completed
... A73: ORD10073 | B73: C008 | C73: P103 | D73: 46004 | E73: 46014 | F73: Kavya Nair | G73: Female | H73: 29851 | I73: Jaipur | J73: North | K73: Electronics | L73: Keyboard | M73: 1 | N73: 1200 | O73: 5 | P73: 1140 | Q73: 3 | R73: UPI | S73: Aisha | T73: kavya.nair@company.com | U73: 9808988530 | V73: Cancelled
A74: ORD10074 | B74: C010 | C74: P202 | D74: 46057 | E74: 46069 | F74: Pooja Shah | G74: Female | H74: 29392 | J74: South | K74: Home Appliances | L74: Iron | M74: 1 | N74: 2200 | O74: 15 | P74: 1870 | Q74: 4 | R74: Card | S74: Aisha | T74: pooja.shah@company.com | U74: 9286410494 | V74: Completed
A75: ORD10075 | B75: C003 | C75: P103 | D75: 46048 | E75: 46050 | F75: Rohit Singh | G75: Male | H75: 30257 | I75: Pune | J75: West | K75: Electronics | L75: Keyboard | M75: 3 | N75: 1200 | O75: 10 | P75: 3240 | Q75: 5 | R75: Cash | S75: Rahul | T75: rohit.singh@company.com | U75: 9311555196 | V75: Completed
A76: ORD10076 | B76: C008 | C76: P201 | D76: 45835 | E76: 45845 | F76: Kavya Nair | G76: Female | H76: 29230 | I76: Bengaluru | J76: South | K76: Home Appliances | L76: Mixer | M76: 10 | N76: 3500 | O76: 20 | P76: 28000 | Q76: 5 | R76: Card | S76: Ritika | T76: kavya.nair@company.com | U76: 9101810266 | V76: Completed
A77: ORD10077 | B77: C007 | C77: P102 | D77: 46098 | E77: 46100 | F77: Arjun Rao | G77: Male | H77: 29703 | I77: Delhi | J77: North | K77: Electronics | L77: Mouse | M77: 18 | N77: 700 | O77: 5 | P77: 11970 | Q77: 3 | R77: Card | S77: Neha | T77: arjun.rao@company.com | U77: 9464556593 | V77: Cancelled
A78: ORD10078 | B78: C005 | C78: P102 | D78: 45817 | E78: 45826 | F78: Vikas Mehta | G78: Male | H78: 31118 | I78: Bengaluru | J78: South | K78: Electronics | L78: Mouse | M78: 12 | N78: 700 | O78: 15 | P78: 7140 | Q78: 2 | R78: UPI | S78: Rahul | T78: vikas.mehta@company.com | U78: 9338278358 | V78: Completed
A79: ORD10079 | B79: C009 | C79: P103 | D79: 45976 | E79: 45977 | F79: Mohit Verma | G79: Male | H79: 36234 | I79: Mumbai | J79: West | K79: Electronics | L79: Keyboard | M79: 8 | N79: 1200 | O79: 0 | P79: 9600 | Q79: 4 | R79: Card | S79: Rahul | T79: mohit.verma@company.com | U79: 9621410770 | V79: Pending
A80: ORD10080 | B80: C003 | C80: P301 | D80: 45967 | E80: 45971 | F80: Rohit Singh | G80: Male | H80: 30504 | I80: Pune | J80: West | K80: Stationery | L80: Notebook | M80: 2 | N80: 60 | O80: 0 | P80: 120 | Q80: 2 | R80: UPI | S80: Rahul | T80: rohit.singh@company.com | U80: 9981333189 | V80: Completed
A81: ORD10081 | B81: C001 | C81: P303 | D81: 45658 | E81: 45664 | F81: Amit Sharma | G81: Male | H81: 32573 | I81: Pune | J81: West | K81: Stationery | L81: Marker | M81: 10 | N81: 45 | O81: 15 | P81: 382.5 | Q81: 3 | R81: NetBanking | S81: Ritika | T81: amit.sharma@company.com | U81: 9723450355 | V81: Cancelled
A82: ORD10082 | B82: C005 | C82: P201 | D82: 46137 | E82: 46145 | F82: Vikas Mehta | G82: Male | H82: 30122 | I82: Kolkata | J82: East | K82: Home Appliances | L82: Mixer | M82: 12 | N82: 3500 | O82: 5 | P82: 39900 | Q82: 3 | R82: NetBanking | S82: Aisha | T82: vikas.mehta@company.com | U82: 9886243907 | V82: Pending
A83: ORD10083 | B83: C003 | C83: P301 | D83: 45919 | E83: 45927 | F83: Rohit Singh | G83: Male | H83: 37065 | I83: Mumbai | J83: West | K83: Stationery | L83: Notebook | M83: 2 | N83: 60 | O83: 15 | P83: 102 | Q83: 1 | R83: UPI | S83: Neha | T83: rohit.singh@company.com | U83: 9473931904 | V83: Completed
A84: ORD10084 | B84: C003 | C84: P103 | D84: 45734 | E84: 45737 | F84: Rohit Singh | G84: Male | H84: 30516 | I84: Hyderabad | J84: South | K84: Electronics | L84: Keyboard | M84: 18 | N84: 1200 | O84: 15 | P84: 18360 | Q84: 3 | R84: Card | S84: Neha | T84: rohit.singh@company.com | U84: 9287159610 | V84: Pending
A85: ORD10085 | B85: C008 | C85: P104 | D85: 45960 | E85: 45961 | F85: Kavya Nair | G85: Female | H85: 34052 | I85: Mumbai | J85: West | K85: Electronics | L85: Monitor | M85: 18 | N85: 12000 | O85: 15 | P85: 183600 | Q85: 2 | R85: Cash | S85: Rahul | T85: kavya.nair@company.com | U85: 9876513858 | V85: Completed
A86: ORD10086 | B86: C007 | C86: P302 | D86: 45961 | E86: 45972 | F86: Arjun Rao | G86: Male | H86: 34829 | I86: Ahmedabad | J86: West | K86: Stationery | L86: Pen | M86: 7 | N86: 20 | O86: 0 | P86: 140 | Q86: 2 | R86: Card | S86: Ritika | T86: arjun.rao@company.com | U86: 9237400853 | V86: Cancelled
... A118: ORD10118 | B118: C001 | C118: P303 | D118: 45808 | E118: 45819 | F118: Amit Sharma | G118: Male | H118: 34949 | I118: Pune | J118: West | K118: Stationery | L118: Marker | M118: 16 | N118: 45 | O118: 0 | P118: 720 | Q118: 1 | R118: NetBanking | S118: Aisha | T118: amit.sharma@company.com | U118: 9807154421 | V118: Completed
A119: ORD10119 | B119: C009 | C119: P103 | D119: 45807 | E119: 45810 | F119: Mohit Verma | G119: Male | H119: 32210 | I119: Ahmedabad | J119: West | K119: Electronics | L119: Keyboard | M119: Ten | N119: 1200 | O119: 15 | P119: 7140 | Q119: 4 | R119: UPI | S119: Karan | T119: mohit.verma@company.com | U119: 9919834000 | V119: Pending
A120: ORD10120 | B120: C002 | C120: P104 | D120: 45888 | E120: 45899 | F120: Priya Patel | G120: Female | H120: 32696 | I120: Jaipur | J120: North | K120: Electronics | L120: Monitor | M120: 14 | N120: 12000 | O120: 15 | P120: 142800 | Q120: 2 | R120: NetBanking | S120: Aisha | T120: priya.patel@company.com | U120: 9739798818 | V120: Pending
A121: ORD10121 | B121: C003 | C121: P203 | D121: 46005 | E121: 46007 | F121: Rohit Singh | G121: Male | H121: 34284 | I121: Pune | J121: West | K121: Home Appliances | L121: Microwave | M121: 8 | N121: 8500 | O121: 20 | P121: 54400 | Q121: 3 | R121: Card | S121: Rahul | T121: rohit.singh@company.com | U121: 9208625306 | V121: Completed
A122: ORD10122 | B122: C007 | C122: P303 | D122: 46053 | E122: 46063 | F122: Arjun Rao | G122: Male | H122: 36557 | I122: Bengaluru | J122: South | K122: Stationery | L122: Marker | M122: 3 | N122: 45 | O122: 0 | P122: 135 | Q122: 4 | R122: UPI | S122: Aisha | T122: arjun.rao@company.com | U122: 9970178536 | V122: Cancelled
A123: ORD10123 | B123: C001 | C123: P102 | D123: 46025 | E123: 46026 | F123: Amit Sharma | G123: Male | H123: 31585 | I123: Jaipur | J123: North | K123: Electronics | L123: Mouse | M123: 13 | N123: 700 | O123: 5 | P123: 8645 | Q123: 3 | R123: Card | S123: Neha | T123: amit.sharma@company.com | U123: 9633745195 | V123: Pending
A124: ORD10124 | B124: C004 | C124: P103 | D124: 45950 | E124: 45956 | F124: Anita Gupta | G124: Female | H124: 31459 | I124: Mumbai | J124: West | K124: Electronics | L124: Keyboard | M124: 14 | N124: 1200 | O124: 20 | P124: 13440 | Q124: 5 | R124: NetBanking | S124: Aisha | T124: anita.gupta@company.com | U124: 9922102053 | V124: Completed
A125: ORD10125 | B125: C002 | C125: P303 | D125: 45788 | E125: 45798 | F125: Priya Patel | G125: Female | H125: 33499 | I125: Delhi | J125: North | K125: Stationery | L125: Marker | M125: 2 | N125: 45 | O125: 5 | P125: 85.5 | Q125: 3 | R125: UPI | S125: Ritika | T125: priya.patel@company.com | U125: 9135963930 | V125: Cancelled
A126: ORD10126 | B126: C004 | C126: P103 | D126: 46024 | E126: 46028 | F126: Anita Gupta | G126: Female | H126: 29590 | I126: Bengaluru | J126: South | K126: Electronics | L126: Keyboard | M126: 2 | N126: 1200 | O126: 20 | P126: 1920 | Q126: 3 | R126: Card | S126: Neha | T126: anita.gupta@company.com | U126: 9429405275 | V126: Completed
A127: ORD10127 | B127: C003 | C127: P101 | D127: 46132 | E127: 46138 | F127: Rohit Singh | G127: Male | H127: 38272 | I127: Bengaluru | J127: South | K127: Electronics | L127: Laptop | M127: 10 | N127: 55000 | O127: 5 | P127: 522500 | Q127: 5 | R127: UPI | S127: Aisha | T127: rohit.singh@company.com | U127: 9521757571 | V127: Pending
A128: ORD10128 | B128: C006 | C128: P201 | D128: 45873 | E128: 45874 | F128: Sneha Joshi | G128: Female | H128: 30766 | I128: Jaipur | J128: North | K128: Home Appliances | L128: Mixer | M128: 15 | N128: 3500 | O128: 10 | P128: 47250 | Q128: 3 | R128: NetBanking | S128: Neha | T128: sneha.joshi@company.com | U128: 9467375455 | V128: Completed
A129: ORD10129 | B129: C002 | C129: P202 | D129: 45882 | E129: 45887 | F129: Priya Patel | G129: Female | H129: 30203 | I129: Bengaluru | J129: South | K129: Home Appliances | L129: Iron | M129: 10 | N129: 2200 | O129: 15 | P129: 18700 | Q129: 4 | R129: Card | S129: Rahul | T129: priya.patel@company.com | U129: 9838809695 | V129: Pending
A130: ORD10130 | B130: C006 | C130: P201 | D130: 45824 | E130: 45832 | F130: Sneha Joshi | G130: Female | H130: 34015 | I130: Pune | J130: West | K130: Home Appliances | L130: Mixer | M130: 11 | N130: 3500 | O130: 5 | P130: 36575 | Q130: 5 | R130: Cash | S130: Ritika | T130: sneha.joshi@company.com | U130: 9296609782 | V130: Cancelled
A131: ORD10131 | B131: C004 | C131: P103 | D131: 46139 | E131: 46142 | F131: Anita Gupta | G131: Female | H131: 37719 | I131: Bengaluru | J131: South | K131: Electronics | L131: Keyboard | M131: 14 | N131: 1200 | O131: 0 | P131: 16800 | Q131: 5 | R131: Cash | S131: Rahul | T131: anita.gupta@company.com | U131: 9848259992 | V131: Cancelled
... A431: ORD10432 | B431: C006 | C431: P104 | D431: 46036 | E431: 46046 | F431: Sneha Joshi | G431: Female | H431: 27550 | I431: Mumbai | J431: West | K431: Electronics | L431: Monitor | M431: 7 | N431: 12000 | O431: 5 | P431: 79800 | Q431: 4 | R431: Card | S431: Karan | T431: sneha.joshi@company.com | U431: 9937007439 | V431: Cancelled
A432: ORD10433 | B432: C001 | C432: P302 | D432: 46152 | E432: Pending | F432: Amit Sharma | G432: Male | H432: 35514 | I432: Kolkata | J432: East | K432: Stationery | L432: Pen | M432: 8 | N432: 20 | O432: 0 | P432: 160 | Q432: 4 | R432: Card | S432: Aisha | T432: amit.sharma@company.com | U432: 9657513435 | V432: Pending
A433: ORD10434 | B433: C008 | C433: P201 | D433: 45689 | E433: 45694 | F433: Kavya Nair | G433: Female | H433: 35538 | I433: Kolkata | J433: East | K433: Home Appliances | L433: Mixer | M433: 16 | N433: 3500 | O433: 5 | P433: 53200 | Q433: 1 | R433: Card | S433: Aisha | T433: kavya.nair@company.com | U433: 9999406260 | V433: Cancelled
A434: ORD10435 | B434: C001 | C434: P203 | D434: 45710 | E434: 45720 | F434: Amit Sharma | G434: Male | H434: 36308 | I434: Mumbai | J434: West | K434: Home Appliances | L434: Microwave | M434: 12 | N434: 8500 | O434: 10 | P434: 91800 | Q434: 3 | R434: Card | S434: Ritika | T434: amit.sharma@company.com | U434: 9233727886 | V434: Completed
A435: ORD10436 | B435: C008 | C435: P301 | D435: 45765 | E435: 45767 | F435: Kavya Nair | G435: Female | H435: 30492 | I435: Ahmedabad | J435: West | K435: Stationery | L435: Notebook | M435: 1 | N435: 60 | O435: 20 | P435: 48 | Q435: 2 | R435: Card | S435: Karan | T435: kavya.nair@company.com | U435: 9831688801 | V435: Completed
A436: ORD10437 | B436: C003 | C436: P301 | D436: 45967 | E436: 45972 | F436: Rohit Singh | G436: Male | H436: 33995 | I436: Hyderabad | J436: South | K436: Stationery | L436: Notebook | M436: 3 | N436: 60 | O436: 15 | P436: 153 | Q436: 4 | R436: Card | S436: Ritika | T436: rohit.singh@company.com | U436: 9982849508 | V436: Completed
A437: ORD10438 | B437: C002 | C437: P102 | D437: 45736 | E437: 45741 | F437: Priya Patel | G437: Female | H437: 28917 | I437: Kolkata | J437: East | K437: Electronics | L437: Mouse | M437: 10 | N437: 700 | O437: 15 | P437: 5950 | Q437: 3 | R437: NetBanking | S437: Ritika | T437: priya.patel@company.com | U437: 9288309246 | V437: Pending
A438: ORD10439 | B438: C007 | C438: P302 | D438: 45952 | E438: 45955 | F438: Arjun Rao | G438: Male | H438: 28016 | I438: Ahmedabad | J438: West | K438: Stationery | L438: Pen | M438: 2 | N438: 20 | O438: 10 | P438: 36 | Q438: 2 | R438: UPI | S438: Aisha | T438: arjun.rao@company.com | U438: 9808476235 | V438: Completed
A439: ORD10440 | B439: C007 | C439: P302 | D439: 46022 | E439: 46027 | F439: Arjun Rao | G439: Male | H439: 33446 | I439: Delhi | J439: North | K439: Stationery | L439: Pen | M439: 14 | N439: 20 | O439: 20 | P439: 224 | Q439: 5 | R439: Cash | S439: Karan | T439: arjun.rao@company.com | U439: 9869056117 | V439: Pending
A440: ORD10441 | B440: C001 | C440: P201 | D440: 45829 | E440: 45833 | F440: Amit Sharma | G440: Male | H440: 32075 | I440: Ahmedabad | J440: West | K440: Home Appliances | L440: Mixer | M440: 4 | N440: 3500 | O440: 0 | P440: 14000 | Q440: 2 | R440: UPI | S440: Ritika | T440: amit.sharma@company.com | U440: 9734229772 | V440: Cancelled
A441: ORD10442 | B441: C007 | C441: P201 | D441: 45812 | E441: 45813 | F441: Arjun Rao | G441: Male | H441: 30629 | I441: Jaipur | J441: North | K441: Home Appliances | L441: Mixer | M441: 9 | N441: 3500 | O441: 5 | P441: 29925 | Q441: 3 | R441: Card | S441: Aisha | T441: arjun.rao@company.com | U441: 9791617906 | V441: Completed
A442: ORD10443 | B442: C003 | C442: P301 | D442: 45807 | E442: 45811 | F442: Rohit Singh | G442: Male | H442: 30678 | I442: Mumbai | J442: West | K442: Stationery | L442: Notebook | M442: 9 | N442: 60 | O442: 0 | P442: 540 | Q442: 3 | R442: UPI | S442: Ritika | T442: rohit.singh@company.com | U442: 9286316823 | V442: Pending
A443: ORD10444 | B443: C004 | C443: P103 | D443: 45779 | E443: 45780 | F443: Anita Gupta | G443: Female | H443: 33862 | I443: Ahmedabad | J443: West | K443: Electronics | L443: Keyboard | M443: 4 | N443: 1200 | O443: 0 | P443: 4800 | Q443: 1 | R443: NetBanking | S443: Aisha | T443: anita.gupta@company.com | U443: 9810569252 | V443: Completed
A444: ORD10445 | B444: C010 | C444: P101 | D444: 45691 | E444: 45701 | F444: Pooja Shah | G444: Female | H444: 36381 | I444: Hyderabad | J444: South | K444: Electronics | L444: Laptop | M444: 10 | N444: 55000 | O444: 5 | P444: 522500 | Q444: 5 | R444: UPI | S444: Neha | T444: pooja.shah@company.com | U444: 9771745925 | V444: Completed
... A499: ORD10500 | B499: C002 | C499: P201 | D499: 45916 | E499: 45923 | F499: Priya Patel | G499: Female | H499: 28088 | I499: Bengaluru | J499: South | K499: Home Appliances | L499: Mixer | M499: 20 | N499: 3500 | O499: 0 | P499: 70000 | Q499: 1 | R499: NetBanking | S499: Karan | T499: priya.patel@company.com | U499: 9810334941 | V499: Pending

Sheet Q10_Sales_Dashboard

Sheet Q10
A1: KPIs
A2: Sum of Sales | C2: Count of Order_ID | E2: Average of Sales
A3: 34745968 | C3: 498 | E3: 69771.019
A4: =GETPIVOTDATA("Sales",$A$2) -> 34745968 | C4: =GETPIVOTDATA("Order_ID",$C$2) -> 498 | E4: =GETPIVOTDATA("Sales",$E$2) -> 69771.019
A7: Row Labels | B7: Sum of Sales | J7: Row Labels | K7: Sum of Sales
A8: East | B8: 4041922 | J8: Electronics | K8: 27823939
A9: North | B9: 10013332 | J9: Home Appliances | K9: 6806525
A10: South | B10: 7487181.5 | J10: Stationery | K10: 115503.5
A11: West | B11: 13203532 | J11: Grand Total | K11: 34745968
A12: Grand Total | B12: 34745968
H16: Row Labels | I16: Sum of Sales
H17: Jan | I17: 5404197.5
H18: Feb | I18: 4363982.2
H19: Mar | I19: 3640969.8
H20: Apr | I20: 5689717.8
H21: May | I21: 3849232
H22: Jun | I22: 1032385
H23: Jul | I23: 1741047.5
H24: Aug | I24: 1836526
H25: Sep | I25: 1226591.5
H26: Oct | I26: 1782743.5
H27: Nov | I27: 1992715.2
H28: Dec | I28: 2185859.5
H29: Grand Total | I29: 34745968
